setup.py
concurrent_server/__init__.py
concurrent_server/servers.py
concurrent_server/management/__init__.py
concurrent_server/management/commands/__init__.py
concurrent_server/management/commands/runcserver.py
django_concurrent_server.egg-info/PKG-INFO
django_concurrent_server.egg-info/SOURCES.txt
django_concurrent_server.egg-info/dependency_links.txt
django_concurrent_server.egg-info/top_level.txt
django_concurrent_server.egg-info/zip-safe