Metadata-Version: 1.1
Name: django-concurrent-server
Version: 0.1.4
Summary: Provides a multi-threaded (concurrent) development sever for Django.
Home-page: https://github.com/ashchristopher/django-concurrent-server
Author: Istvan Albert, James Aylett, Ash Christopher, Pablo Martin
Author-email: ash.christopher@gmail.ca
License: MIT
Download-URL: https://github.com/ashchristopher/django-concurrent-server
Platform: UNKNOWN
Classifier: Development Status :: 4 - Beta
Classifier: Environment :: Web Environment
Classifier: Framework :: Django
Classifier: Intended Audience :: Developers
Classifier: Operating System :: OS Independent
Classifier: Programming Language :: Python
Classifier: Topic :: Software Development :: Libraries :: Python Modules
